{
    "RO": {
        "now": "2024-04-25T15:00:00",
        "temp": 18.1
    },
    "JMAJapan": [
        {
            "now": "2024-04-25T15:00:00",
            "temp": 16.3
        },
        {
            "now": "2024-04-25T21:00:00",
            "temp": 11.4
        },
        {
            "now": "2024-04-26T03:00:00",
            "temp": 8.2
        },
        {
            "now": "2024-04-26T09:00:00",
            "temp": 9.5
        },
        {
            "now": "2024-04-26T15:00:00",
            "temp": 14.5
        },
        {
            "now": "2024-04-26T21:00:00",
            "temp": 10.3
        },
        {
            "now": "2024-04-27T03:00:00",
            "temp": 7.1
        },
        {
            "now": "2024-04-27T09:00:00",
            "temp": 14.5
        },
        {
            "now": "2024-04-27T15:00:00",
            "temp": 19.1
        },
        {
            "now": "2024-04-27T21:00:00",
            "temp": 14.2
        },
        {
            "now": "2024-04-28T03:00:00",
            "temp": 10.1
        },
        {
            "now": "2024-04-28T09:00:00",
            "temp": 15.6
        },
        {
            "now": "2024-04-28T15:00:00",
            "temp": 20.5
        },
        {
            "now": "2024-04-28T21:00:00",
            "temp": 14.4
        },
        {
            "now": "2024-04-29T03:00:00",
            "temp": 10.1
        },
        {
            "now": "2024-04-29T09:00:00",
            "temp": 15.8
        },
        {
            "now": "2024-04-29T15:00:00",
            "temp": 21.4
        },
        {
            "now": "2024-04-29T21:00:00",
            "temp": 16.0
        },
        {
            "now": "2024-04-30T03:00:00",
            "temp": 11.9
        },
        {
            "now": "2024-04-30T09:00:00",
            "temp": 15.9
        },
        {
            "now": "2024-04-30T15:00:00",
            "temp": 22.4
        },
        {
            "now": "2024-04-30T21:00:00",
            "temp": 16.9
        },
        {
            "now": "2024-05-01T03:00:00",
            "temp": 12.7
        },
        {
            "now": "2024-05-01T09:00:00",
            "temp": 16.8
        },
        {
            "now": "2024-05-01T15:00:00",
            "temp": 21.6
        },
        {
            "now": "2024-05-01T21:00:00",
            "temp": 14.4
        }
    ]
}